aliyunsdkadcp/__init__.py
aliyunsdkadcp/endpoint.py
aliyunsdkadcp/request/__init__.py
aliyunsdkadcp/request/v20220101/AttachClusterToHubRequest.py
aliyunsdkadcp/request/v20220101/CreateHubClusterRequest.py
aliyunsdkadcp/request/v20220101/DeleteHubClusterRequest.py
aliyunsdkadcp/request/v20220101/DeletePolicyInstanceRequest.py
aliyunsdkadcp/request/v20220101/DeleteUserPermissionRequest.py
aliyunsdkadcp/request/v20220101/DeployPolicyInstanceRequest.py
aliyunsdkadcp/request/v20220101/DescribeHubClusterDetailsRequest.py
aliyunsdkadcp/request/v20220101/DescribeHubClusterKubeconfigRequest.py
aliyunsdkadcp/request/v20220101/DescribeHubClusterLogsRequest.py
aliyunsdkadcp/request/v20220101/DescribeHubClustersRequest.py
aliyunsdkadcp/request/v20220101/DescribeManagedClustersRequest.py
aliyunsdkadcp/request/v20220101/DescribePoliciesRequest.py
aliyunsdkadcp/request/v20220101/DescribePolicyDetailsRequest.py
aliyunsdkadcp/request/v20220101/DescribePolicyGovernanceInClusterRequest.py
aliyunsdkadcp/request/v20220101/DescribePolicyInstancesRequest.py
aliyunsdkadcp/request/v20220101/DescribePolicyInstancesStatusRequest.py
aliyunsdkadcp/request/v20220101/DescribeRegionsRequest.py
aliyunsdkadcp/request/v20220101/DescribeUserPermissionsRequest.py
aliyunsdkadcp/request/v20220101/DetachClusterFromHubRequest.py
aliyunsdkadcp/request/v20220101/GrantUserPermissionRequest.py
aliyunsdkadcp/request/v20220101/GrantUserPermissionsRequest.py
aliyunsdkadcp/request/v20220101/UpdateHubClusterFeatureRequest.py
aliyunsdkadcp/request/v20220101/UpdateUserPermissionRequest.py
aliyunsdkadcp/request/v20220101/__init__.py
aliyun_python_sdk_adcp-1.0.0.dist-info/LICENSE
aliyun_python_sdk_adcp-1.0.0.dist-info/METADATA
aliyun_python_sdk_adcp-1.0.0.dist-info/WHEEL
aliyun_python_sdk_adcp-1.0.0.dist-info/top_level.txt
aliyun_python_sdk_adcp-1.0.0.dist-info/RECORD
